sdqrcode/Engines/AutoEngine.py
sdqrcode/Engines/DiffusersEngine.py
sdqrcode/Engines/Engine.py
sdqrcode/Engines/engine_util.py
sdqrcode/__init__.py
sdqrcode/configs/brightness_auto.yaml
sdqrcode/configs/brightness_diffusers.yaml
sdqrcode/configs/custom.yaml
sdqrcode/configs/default.yaml
sdqrcode/configs/default_auto.yaml
sdqrcode/configs/default_diffusers.yaml
sdqrcode/configs/img2img_tile_auto.yaml
sdqrcode/configs/img2img_tile_diffusers.yaml
sdqrcode/sdqrcode.py
sdqrcode-0.3.12.dist-info/LICENSE
sdqrcode-0.3.12.dist-info/METADATA
sdqrcode-0.3.12.dist-info/WHEEL
sdqrcode-0.3.12.dist-info/RECORD
