Metadata-Version: 2.1
Name: sdqrcode
Version: 0.3.12
Summary: Generate ai qr codes with stable diffusion and controlnet with standardised methods
License: MIT
Author: PhilSad
Author-email: philippe.henri.saade@gmail.com
Requires-Python: >=3.8,<4.0
Classifier: License :: OSI Approved :: MIT License
Classifier: Programming Language :: Python :: 3
Classifier: Programming Language :: Python :: 3.8
Classifier: Programming Language :: Python :: 3.9
Classifier: Programming Language :: Python :: 3.10
Classifier: Programming Language :: Python :: 3.11
Provides-Extra: diffusers
Requires-Dist: PyYAML (>=6.0,<7.0)
Requires-Dist: accelerate (==0.20.0) ; extra == "diffusers"
Requires-Dist: qrcode (>=7.4.1,<8.0.0)
Requires-Dist: transformers (==4.30.0) ; extra == "diffusers"
Requires-Dist: webuiapi (>=0.9.3,<0.10.0)
Requires-Dist: xformers (==0.0.20) ; extra == "diffusers"
